.gitignore
README.md
README.txt
bootstrap.py
buildout.cfg
plone.cfg
setup.cfg
setup.py
docs/HISTORY.txt
docs/INSTALL.txt
docs/LICENSE.GPL
docs/LICENSE.txt
uwosh/__init__.py
uwosh.double_blind_review.egg-info/PKG-INFO
uwosh.double_blind_review.egg-info/SOURCES.txt
uwosh.double_blind_review.egg-info/dependency_links.txt
uwosh.double_blind_review.egg-info/entry_points.txt
uwosh.double_blind_review.egg-info/namespace_packages.txt
uwosh.double_blind_review.egg-info/not-zip-safe
uwosh.double_blind_review.egg-info/paster_plugins.txt
uwosh.double_blind_review.egg-info/requires.txt
uwosh.double_blind_review.egg-info/top_level.txt
uwosh/double_blind_review/.DS_Store
uwosh/double_blind_review/INTEGRATION.txt
uwosh/double_blind_review/__init__.py
uwosh/double_blind_review/configure.zcml
uwosh/double_blind_review/interfaces.py
uwosh/double_blind_review/make_decisions_visible.py
uwosh/double_blind_review/tests.py
uwosh/double_blind_review/locales/README.txt
uwosh/double_blind_review/profiles/.DS_Store
uwosh/double_blind_review/profiles/default/browserlayer.xml
uwosh/double_blind_review/profiles/default/metadata.xml
uwosh/double_blind_review/profiles/default/propertiestool.xml
uwosh/double_blind_review/profiles/default/rolemap.xml
uwosh/double_blind_review/profiles/default/skins.xml
uwosh/double_blind_review/profiles/default/tinymce.xml
uwosh/double_blind_review/profiles/default/types.xml
uwosh/double_blind_review/profiles/default/workflows.xml
uwosh/double_blind_review/profiles/default/skins/.DS_Store
uwosh/double_blind_review/profiles/default/skins/custom.xml
uwosh/double_blind_review/profiles/default/skins/custom/.DS_Store
uwosh/double_blind_review/profiles/default/skins/custom/folder_listing.pt
uwosh/double_blind_review/profiles/default/structure/.objects
uwosh/double_blind_review/profiles/default/structure/acl_users/.DS_Store
uwosh/double_blind_review/profiles/default/structure/acl_users/.objects
uwosh/double_blind_review/profiles/default/structure/acl_users/portal_role_manager.xml
uwosh/double_blind_review/profiles/default/structure/acl_users/source_groups.xml
uwosh/double_blind_review/profiles/default/structure/double-blind-review-instructions/.DS_Store
uwosh/double_blind_review/profiles/default/structure/double-blind-review-instructions/.objects
uwosh/double_blind_review/profiles/default/structure/double-blind-review-instructions/.properties
