Metadata-Version: 1.0
Name: uwosh.double_blind_review
Version: 0.9
Summary: Double Blind Review Workflows
Home-page: https://github.com/gutow/uwosh.double_blind_review
Author: Jonathan Gutow
Author-email: gutow@uwosh.edu
License: GPL
Keywords: review,double-blind,double-blind review,proposals,dropbox
Platform: UNKNOWN
Classifier: Framework :: Plone
Classifier: Programming Language :: Python
Classifier: Topic :: Software Development :: Libraries :: Python Modules
